gymnasium_2048/__init__.py
gymnasium_2048/agents/__init__.py
gymnasium_2048/agents/ntuple/__init__.py
gymnasium_2048/agents/ntuple/factory.py
gymnasium_2048/agents/ntuple/network.py
gymnasium_2048/agents/ntuple/policy.py
gymnasium_2048/envs/__init__.py
gymnasium_2048/envs/twenty_forty_eight.py
gymnasium_2048/wrappers/__init__.py
gymnasium_2048/wrappers/illegal_reward.py
gymnasium_2048/wrappers/terminate_goal.py
gymnasium_2048/wrappers/terminate_illegal.py
gymnasium_2048-0.0.2.dist-info/LICENSE
gymnasium_2048-0.0.2.dist-info/METADATA
gymnasium_2048-0.0.2.dist-info/WHEEL
gymnasium_2048-0.0.2.dist-info/top_level.txt
gymnasium_2048-0.0.2.dist-info/RECORD
