Metadata-Version: 2.1
Name: gymnasium_2048
Version: 0.0.2
Summary: A reinforcement learning environment for the 2048 game based on Gymnasium
Author-email: Quentin Deschamps <quentindeschamps18@gmail.com>
License: MIT
Project-URL: Repository, https://github.com/Quentin18/gymnasium-2048
Keywords: 2048,Reinforcement Learning,game,RL,AI,gymnasium,pygame
Classifier: License :: OSI Approved :: MIT License
Classifier: Programming Language :: Python :: 3
Classifier: Programming Language :: Python :: 3.10
Classifier: Programming Language :: Python :: 3.11
Classifier: Programming Language :: Python :: 3.12
Classifier: Topic :: Games/Entertainment
Classifier: Topic :: Scientific/Engineering :: Artificial Intelligence
Requires-Python: >=3.10
License-File: LICENSE
Requires-Dist: gymnasium==0.29.1
Requires-Dist: pygame==2.6.1
Provides-Extra: training
Requires-Dist: matplotlib==3.9.3; extra == "training"
Requires-Dist: moviepy==2.1.1; extra == "training"
Requires-Dist: pandas==2.2.3; extra == "training"
Requires-Dist: pyarrow==18.1.0; extra == "training"
Requires-Dist: tqdm==4.67.1; extra == "training"
Provides-Extra: testing
Requires-Dist: pytest; extra == "testing"
Provides-Extra: quality
Requires-Dist: black[d]; extra == "quality"
Requires-Dist: isort; extra == "quality"
Requires-Dist: pylint; extra == "quality"
